rightness/__init__.py
rightness-0.0.4.dist-info/LICENSE.txt
rightness-0.0.4.dist-info/METADATA
rightness-0.0.4.dist-info/WHEEL
rightness-0.0.4.dist-info/top_level.txt
rightness-0.0.4.dist-info/RECORD
