Metadata-Version: 2.1
Name: rightness
Version: 0.0.4
Summary: rightness
Author-email: Johannes <johannes-programming@mailfence.com>
License: The MIT License (MIT)
Project-URL: Download, https://pypi.org/project/rightness/#files
Project-URL: Source, https://github.com/johannes-programming/rightness
Classifier: License :: OSI Approved :: MIT License
Classifier: Programming Language :: Python
Classifier: Programming Language :: Python :: 3
Requires-Python: >=3.11
License-File: LICENSE.txt
